stvh/micronn/__init__.py
stvh-0.1.0.dist-info/METADATA
stvh-0.1.0.dist-info/WHEEL
stvh-0.1.0.dist-info/top_level.txt
stvh-0.1.0.dist-info/RECORD
