Metadata-Version: 2.1
Name: stvh
Version: 0.1.0
License: MIT
Requires-Dist: beartype
